{
    "meta" : {
        "label": "Zendesk password access",
        "description": "Connect to Zendesk using your user name / password",
        "icon": "icon-ticket"
    },
    "defaultDefinableInline": true,
    "defaultDefinableAtProjectLevel": true,
    "pluginParams": [
    ],

    "params": [
        {
            "name": "zendesk_subdomain",
            "label": "Subdomain",
            "type": "STRING",
            "description": "Usually your company name",
            "defaultValue" : ""
        },
        {
            "name": "zendesk_username",
            "label": "Username",
            "type": "STRING",
            "description": "Usually your email address",
            "defaultValue" : ""
        },
        {
            "name": "zendesk_password",
            "label": "Password",
            "type": "PASSWORD",
            "defaultValue" : ""
        }
    ]
}
